cyext_acv.cpython-310-x86_64-linux-gnu.so
cyext_acv_nopa.cpython-310-x86_64-linux-gnu.so
cext_acv.cpython-310-x86_64-linux-gnu.so
cyext_acv_cache.cpython-310-x86_64-linux-gnu.so
acv_explainers/acv_tree.py
acv_explainers/setup.py
acv_explainers/utils_exp.py
acv_explainers/base_tree.py
acv_explainers/py_acv.py
acv_explainers/base_agnostree.py
acv_explainers/acv_agnosticX.py
acv_explainers/utils_sdp.py
acv_explainers/counterfactual_rules.py
acv_explainers/utils_cr.py
acv_explainers/utils.py
acv_explainers/__init__.py
experiments/exp_linear_gmm_ohe.py
experiments/exp_syn.py
experiments/exp_linear.py
experiments/shap_linear.py
experiments/utils.py
experiments/__init__.py
experiments/exp_linear_gmm.py
acv_dev.libs/libgomp-a34b3233.so.1.0.0
acv_app/sv_app.py
acv_app/sdp_app.py
acv_app/app.py
acv_app/plots.py
acv_app/__init__.py
acv_app/colors/_colorconv.py
acv_app/colors/_colors.py
acv_app/colors/__init__.py
acv_dev-0.0.15.dist-info/top_level.txt
acv_dev-0.0.15.dist-info/WHEEL
acv_dev-0.0.15.dist-info/METADATA
acv_dev-0.0.15.dist-info/RECORD
acv_dev-0.0.15.dist-info/LICENSE
